pydepsdev/__init__.py
pydepsdev/api.py
pydepsdev/constants.py
pydepsdev/exceptions.py
pydepsdev/utils.py
pydepsdev-0.2.3.dist-info/licenses/LICENSE
pydepsdev-0.2.3.dist-info/METADATA
pydepsdev-0.2.3.dist-info/WHEEL
pydepsdev-0.2.3.dist-info/top_level.txt
pydepsdev-0.2.3.dist-info/RECORD
