Metadata-Version: 2.4
Name: pydepsdev
Version: 0.2.3
Summary: A Python library for interacting with Open Source Insights API (deps.dev)
Author-email: Robert-André Mauchin <eclipseo@mauchin.fr>
License-Expression: Apache-2.0
Project-URL: Homepage, https://codeberg.org/eclipseo/pydepsdev
Project-URL: Repository, https://codeberg.org/eclipseo/pydepsdev.git
Project-URL: Bug Tracker, https://codeberg.org/eclipseo/pydepsdev/issues
Keywords: Open Source Insights,api,deps.dev
Classifier: Topic :: Software Development :: Libraries
Classifier: Development Status :: 4 - Beta
Classifier: Programming Language :: Python :: 3
Classifier: Operating System :: OS Independent
Classifier: Intended Audience :: Developers
Requires-Python: >=3.9
License-File: LICENSE
Requires-Dist: aiohttp
Dynamic: license-file
